odoo/addons/edi_backend_partner_oca/README.rst
odoo/addons/edi_backend_partner_oca/__init__.py
odoo/addons/edi_backend_partner_oca/__manifest__.py
odoo/addons/edi_backend_partner_oca/i18n/edi_backend_partner.pot
odoo/addons/edi_backend_partner_oca/i18n/edi_backend_partner_oca.pot
odoo/addons/edi_backend_partner_oca/models/__init__.py
odoo/addons/edi_backend_partner_oca/models/edi_backend.py
odoo/addons/edi_backend_partner_oca/models/res_partner.py
odoo/addons/edi_backend_partner_oca/readme/CONTRIBUTORS.rst
odoo/addons/edi_backend_partner_oca/readme/DESCRIPTION.rst
odoo/addons/edi_backend_partner_oca/static/description/icon.png
odoo/addons/edi_backend_partner_oca/static/description/index.html
odoo/addons/edi_backend_partner_oca/tests/__init__.py
odoo/addons/edi_backend_partner_oca/tests/test_edi_backend_partner.py
odoo/addons/edi_backend_partner_oca/views/edi_backend_views.xml
odoo/addons/edi_backend_partner_oca/views/res_partner_views.xml
odoo14_addon_edi_backend_partner_oca-14.0.1.0.1.dist-info/METADATA
odoo14_addon_edi_backend_partner_oca-14.0.1.0.1.dist-info/WHEEL
odoo14_addon_edi_backend_partner_oca-14.0.1.0.1.dist-info/top_level.txt
odoo14_addon_edi_backend_partner_oca-14.0.1.0.1.dist-info/RECORD
